scm20367104703/__init__.py
scm20367104703/lab2mod167104703.py
scm20367104703/lab2mod267104703.py
scm20367104703-0.1.1.dist-info/METADATA
scm20367104703-0.1.1.dist-info/WHEEL
scm20367104703-0.1.1.dist-info/top_level.txt
scm20367104703-0.1.1.dist-info/RECORD
