Metadata-Version: 2.4
Name: scm20367104703
Version: 0.1.1
Summary: This is package . A example package to find Roots of eqaution and solves an ordinary differential equation (ODE).
Home-page: https://github.com/Amarit1008/ammaritproj
Author: N. Amarittabut
Author-email: nabeel65010@email.com
Requires-Python: >=3.8
Dynamic: author
Dynamic: author-email
Dynamic: description
Dynamic: description-content-type
Dynamic: home-page
Dynamic: requires-python
Dynamic: summary
